carbon_slack/__init__.py
carbon_slack/carbon.py
carbon_slack/command.py
carbon_slack/config.py
carbon_slack/relay.py
carbon_slack/slack.py
carbon_slack-0.0.8.dist-info/METADATA
carbon_slack-0.0.8.dist-info/RECORD
carbon_slack-0.0.8.dist-info/WHEEL
carbon_slack-0.0.8.dist-info/entry_points.txt
carbon_slack-0.0.8.dist-info/top_level.txt
carbon_slack-0.0.8.dist-info/zip-safe
