Metadata-Version: 2.1
Name: carbon-slack
Version: 0.0.8
Summary: Use Slack as a bus for GraphiteDB / Carbon
Home-page: https://github.com/jdcasey/carbon-slack
Author: John Casey
Author-email: jdcasey@commonjava.org
License: GPLv3+
Keywords: graphite carbon metrics monitoring slack
Platform: UNKNOWN
Classifier: Development Status :: 3 - Alpha
Classifier: Intended Audience :: Developers
Classifier: License :: OSI Approved :: GNU General Public License (GPL)
Classifier: Programming Language :: Python :: 2
Classifier: Topic :: Utilities
Requires-Dist: slackclient
Requires-Dist: click
Requires-Dist: ruamel.yaml
